bits_and_bobs/__init__.py
bits_and_bobs/caching_utils.py
bits_and_bobs/logging_utils.py
bits_and_bobs/timeout_utils.py
bits_and_bobs-0.2.0.dist-info/METADATA
bits_and_bobs-0.2.0.dist-info/WHEEL
bits_and_bobs-0.2.0.dist-info/licenses/LICENSE
bits_and_bobs-0.2.0.dist-info/RECORD
