Metadata-Version: 2.4
Name: bits_and_bobs
Version: 0.2.0
Summary: General utility functions with no dependencies.
Project-URL: Repository, https://github.com/alexandrainst/bits_and_bobs
Project-URL: Issues, https://github.com/alexandrainst/bits_and_bobs/issues
Author-email: Dan Saattrup Smart <dan.smart@alexandra.dk>
Maintainer-email: Dan Saattrup Smart <dan.smart@alexandra.dk>
License: MIT License
License-File: LICENSE
Requires-Python: <4.0,>=3.11
